antmocdata/__init__.py
antmocdata/log/__init__.py
antmocdata/log/data.py
antmocdata/log/default_fields.json
antmocdata/log/extract.py
antmocdata/log/fields.py
antmocdata/log/options.py
antmocdata/mgxs/__init__.py
antmocdata/mgxs/material.py
antmocdata/mgxs/materialxml.py
antmocdata/mgxs/options.py
antmocdata/mgxs/manip/__init__.py
antmocdata/mgxs/manip/h5.py
antmocdata/mgxs/manip/xml.py
antmocdata/mgxs/type_a/__init__.py
antmocdata/mgxs/type_a/elements.json
antmocdata/mgxs/type_a/generate.py
antmocdata/mgxs/type_a/infilecross.py
antmocdata/mgxs/type_a/material.py
antmocdata/mgxs/type_a/nuclides.py
antmocdata/mgxs/type_a/options.py
antmocdata/solution/__init__.py
antmocdata/solution/rxh5.py
antmocdata/solution/rxvtk.py
antmocdata-0.1.4.dist-info/LICENSE
antmocdata-0.1.4.dist-info/METADATA
antmocdata-0.1.4.dist-info/WHEEL
antmocdata-0.1.4.dist-info/top_level.txt
antmocdata-0.1.4.dist-info/RECORD
