Metadata-Version: 2.1
Name: antmocdata
Version: 0.1.4
Summary: A package for ANT-MOC data manipulation.
Author-email: An Wang <wangan.cs@gmail.com>
License: MIT License
Project-URL: Homepage, https://github.com/alephpiece/antmoc-data
Project-URL: Repository, https://github.com/alephpiece/antmoc-data
Requires-Python: >=3.8
License-File: LICENSE
Requires-Dist: baseopt
Requires-Dist: h5py
Requires-Dist: numpy
Requires-Dist: pyevtk
